<annotation>
  <folder>Images</folder>
  <filename>car115</filename>
  <path>C:\Users\joche\Desktop\JAMK\Internet of Things\CarObjectDetection\Images\car115.jpg</path>
  <source>
    <database>Unknown</database>
  </source>
  <size>
    <width>736</width>
    <height>552</height>
    <depth>3</depth>
  </size>
  <segmented>0</segmented>
  <object>
    <name>car</name>
    <pose>Unspecified</pose>
    <truncated>0</truncated>
    <difficult>0</difficult>
    <bndbox>
      <xmin>35</xmin>
      <ymin>110</ymin>
      <xmax>705</xmax>
      <ymax>491</ymax>
    </bndbox>
  </object>
</annotation>
