<annotation>
  <folder>Images</folder>
  <filename>car2</filename>
  <path>C:\Users\joche\Desktop\JAMK\Internet of Things\CarObjectDetection\Images\car2.jpg</path>
  <source>
    <database>Unknown</database>
  </source>
  <size>
    <width>541</width>
    <height>408</height>
    <depth>3</depth>
  </size>
  <segmented>0</segmented>
  <object>
    <name>car</name>
    <pose>Unspecified</pose>
    <truncated>0</truncated>
    <difficult>0</difficult>
    <bndbox>
      <xmin>60</xmin>
      <ymin>129</ymin>
      <xmax>486</xmax>
      <ymax>313</ymax>
    </bndbox>
  </object>
</annotation>
